setup.py
UMGrader/__init__.py
UMGrader/circle.py
UMGrader.egg-info/PKG-INFO
UMGrader.egg-info/SOURCES.txt
UMGrader.egg-info/dependency_links.txt
UMGrader.egg-info/top_level.txt