Metadata-Version: 2.1
Name: UMGrader
Version: 0.1
Summary: Grading system for ipynb
Author: Sittha Darapisut
